concrete/__init__.py
concrete/__main__.py
concrete/abstract.py
concrete/celery.py
concrete/celeryconfig.py
concrete/clients.py
concrete/db/__init__.py
concrete/db/crud.py
concrete/db/orm/__init__.py
concrete/db/orm/models.py
concrete/db/orm/setup.py
concrete/models/base.py
concrete/models/clients.py
concrete/models/messages.py
concrete/models/operations.py
concrete/operators.py
concrete/orchestrator.py
concrete/prompts.py
concrete/state.py
concrete/tools.py
concrete/utils.py
concrete_operators-0.1.11.dist-info/METADATA
concrete_operators-0.1.11.dist-info/WHEEL
concrete_operators-0.1.11.dist-info/RECORD
