Metadata-Version: 2.1
Name: concrete-operators
Version: 0.1.11
Summary: AI Agent Orchestration Platform
Author: Abstract Operators
Author-email: hello@abstractoperators.ai
Requires-Python: >=3.11.9,<4.0.0
Classifier: Programming Language :: Python :: 3
Classifier: Programming Language :: Python :: 3.12
Requires-Dist: astor (==0.8.1)
Requires-Dist: astroid (==3.2.3)
Requires-Dist: celery (==5.4.0)
Requires-Dist: openai (==1.40.5)
Requires-Dist: python-dotenv (==1.0.1)
Requires-Dist: requests (==2.32.3)
Requires-Dist: sqlalchemy (==2.0.34)
Requires-Dist: sqlmodel (==0.0.22)
Requires-Dist: tenacity (==9.0.0)
